motorcalc/__init__.py
motorcalc/dcmotor.py
motorcalc/dcmotorexport.py
motorcalc/dcmotorplot.py
motorcalc/load_dynamics.py
motorcalc/physics/constants.py
motorcalc/physics/inertia.py
motorcalc/physics/kinetics.py
motorcalc-0.2.1.dist-info/METADATA
motorcalc-0.2.1.dist-info/WHEEL
motorcalc-0.2.1.dist-info/licenses/LICENSE.md
motorcalc-0.2.1.dist-info/RECORD
