Metadata-Version: 2.3
Name: motorcalc
Version: 0.2.1
Summary: Add your description here
Author-email: Gerrit Kocherscheidt <kochersg@koco-group.com>
License-File: LICENSE.md
Requires-Python: >=3.8
Requires-Dist: matplotlib>=3.8.4
Requires-Dist: numpy>=1.26.4
Requires-Dist: openpyxl>=3.1.2
Requires-Dist: texttable>=1.7.0
